{
    "name": "孵化器",
    "icon": "productivebees:incubator",
    "category": "productivebees:blocks",
    "pages": [
        {
            "type": "spotlight",
            "item": "productivebees:incubator",
            "text": "厌倦了等待那些脆弱的小宝贝长大？使用小蜜蜂孵化器来加速这个过程。只需将小蜜蜂放入笼子中，然后将其与一堆蜂蜜一起放入孵化器中。"
        },
        {
            "type": "text",
            "text": "孵化器的另一个用途是特定蜜蜂类型，将$(l:genetics/collecting#crystal)基因样本$(/l)注入一个卵中，以获得该蜜蜂类型的刷怪蛋。通过遗传基因设置所获得的蜜蜂卵只携带该类型的基因$(br)。蜂蜜上的任何其他基因都将丢失"
        }
    ]
}
